logdriver/__init__.py
logdriver/cli.py
logdriver/server.py
venv/bin/rst2html.py
venv/bin/rst2html4.py
venv/bin/rst2html5.py
venv/bin/rst2latex.py
venv/bin/rst2man.py
venv/bin/rst2odt.py
venv/bin/rst2odt_prepstyles.py
venv/bin/rst2pseudoxml.py
venv/bin/rst2s5.py
venv/bin/rst2xetex.py
venv/bin/rst2xml.py
venv/bin/rstpep2html.py
logdriver-0.1.5.dist-info/LICENSE
logdriver-0.1.5.dist-info/METADATA
logdriver-0.1.5.dist-info/WHEEL
logdriver-0.1.5.dist-info/entry_points.txt
logdriver-0.1.5.dist-info/top_level.txt
logdriver-0.1.5.dist-info/RECORD
