Metadata-Version: 2.1
Name: logdriver
Version: 0.1.5
Summary: Run a socket server for application logging
Author: Steve King
Author-email: steve@steveking.site
License: MIT License
Project-URL: homepage, https://github.com/sjking/logdriver
Project-URL: repository, https://github.com/sjking/logdriver
Project-URL: documentation, https://github.com/sjking/logdriver
Keywords: logging,logger,microservice,cli
Classifier: Development Status :: 2 - Pre-Alpha
Classifier: Environment :: Console
Classifier: Intended Audience :: Developers
Classifier: Intended Audience :: Information Technology
Classifier: Intended Audience :: Science/Research
Classifier: Intended Audience :: System Administrators
Classifier: License :: OSI Approved :: MIT License
Classifier: Programming Language :: Python :: 3 :: Only
Classifier: Topic :: System :: Distributed Computing
Classifier: Topic :: System :: Logging
Requires-Python: >=3.6
License-File: LICENSE
Provides-Extra: dev
Requires-Dist: pytest ; extra == 'dev'
Requires-Dist: flake8 ; extra == 'dev'
Requires-Dist: black ; extra == 'dev'
Requires-Dist: tox ; extra == 'dev'
Requires-Dist: coverage ; extra == 'dev'
Requires-Dist: build ; extra == 'dev'
Requires-Dist: pip-tools ; extra == 'dev'
